{
    "data": {
        "info": {
            "appid": 90272,
            "id_num": 118741,
            "name_format": "F",
            "last_name": "TAKI",
            "first_name": "Salma",
            "middle_name": null,
            "birth_name": "BJ476811",
            "mobile_phone": 635870672,
            "email_address": "118741@aui.ma",
            "stud_mstr_employ": "E"
        },
        "candiday": [
            {
                "idNum": 118741,
                "yearCode": "2223",
                "divisionCode": "UG",
                "stage": "ENR",
                "programCode": "BBA  ",
                "termCode": "FA",
                "bacYear": "2022",
                "highSchool": "47508",
                "highSchoolDiploma": "1",
                "highSchoolDistinction": "T",
                "hsOrgTypeAd": "HS",
                "gpa": 16.54,
                "totalApCredits": 15,
                "totalInstCredits": 16,
                "clOrgTypeAd": null,
                "clGpa": null,
                "clTotalApCredits": null,
                "clTotalInstCredits": null,
                "schoolType": null,
                "udef1a1": "H",
                "act": null,
                "gat": null,
                "gre": null,
                "sat": null,
                "satRc": null,
                "satWc": null,
                "tef": null,
                "toepp": null,
                "birthDate": "2004-10-19T00:00:00.000+00:00",
                "citizenOf": "MA",
                "city": "CASABLANCA",
                "country": "MA",
                "addressLine1": "RES AL FADL GH 4 IMM 1 NR 4",
                "birthName": "BJ476811",
                "firstName": "Salma",
                "lastName": "TAKI",
                "emailAddress": "118741@aui.ma",
                "gender": "F",
                "mobile": "635870672",
                "fatherAddress": null,
                "motherAddress": null,
                "fatherPhone": null,
                "motherPhone": null,
                "fatherOccupation": null,
                "motherOccupation": null,
                "appFeeDate": "2021-12-27T23:00:00.000+00:00"
            },{
                "idNum": 10000,
                "yearCode": "2223",
                "divisionCode": "UG",
                "stage": "ENR",
                "programCode": "BBA  ",
                "termCode": "FA",
                "bacYear": "2022",
                "highSchool": "47508",
                "highSchoolDiploma": "1",
                "highSchoolDistinction": "T",
                "hsOrgTypeAd": "HS",
                "gpa": 16.54,
                "totalApCredits": 15,
                "totalInstCredits": 16,
                "clOrgTypeAd": null,
                "clGpa": null,
                "clTotalApCredits": null,
                "clTotalInstCredits": null,
                "schoolType": null,
                "udef1a1": "H",
                "act": null,
                "gat": null,
                "gre": null,
                "sat": null,
                "satRc": null,
                "satWc": null,
                "tef": null,
                "toepp": null,
                "birthDate": "2004-10-19T00:00:00.000+00:00",
                "citizenOf": "MA",
                "city": "CASABLANCA",
                "country": "MA",
                "addressLine1": "RES AL FADL GH 4 IMM 1 NR 4",
                "birthName": "BJ476811",
                "firstName": "Salma",
                "lastName": "TAKI",
                "emailAddress": "118741@aui.ma",
                "gender": "F",
                "mobile": "635870672",
                "fatherAddress": null,
                "motherAddress": null,
                "fatherPhone": null,
                "motherPhone": null,
                "fatherOccupation": null,
                "motherOccupation": null,
                "appFeeDate": "2021-12-27T23:00:00.000+00:00"
            }
        ],
        "student": {
            "idNum": 118741,
            "studentEmployCode": "E",
            "webGroup": "07",
            "tuitionCode": "RG",
            "entranceYear": "2223",
            "entranceTerm": "FA",
            "currentClassCode": "JR",
            "hold1Code": null,
            "hold2Code": null,
            "hold3Code": null,
            "hold4Code": null,
            "hold5Code": null,
            "hold6Code": null,
            "numOfCourses": 4,
            "hoursEnrolled": 12,
            "termHoursEarned": 0,
            "careerGpa": 2.68,
            "degreeCode": "BS",
            "major1": "CSC",
            "minor1": null,
            "concentration1": null
        }
    }
}